{
  "_fv": 57,
  "_type": "item",
  "definition": {
    "renderType": 0,
    "texture": "blossom_flora",
    "customModelName": "Tool",
    "customProperties": {},
    "states": [],
    "name": "§aBlossom Flora",
    "rarity": "COMMON",
    "creativeTab": {
      "value": "CUSTOM:Mage"
    },
    "stackSize": 1,
    "enchantability": 8,
    "useDuration": 0,
    "toolType": 1.0,
    "damageCount": 0,
    "recipeRemainder": {
      "value": ""
    },
    "destroyAnyBlock": false,
    "immuneToFire": false,
    "stayInGridWhenCrafting": false,
    "damageOnCrafting": false,
    "enableMeleeDamage": false,
    "damageVsEntity": 0.0,
    "specialInformation": {
      "fixedValue": [
        "§aRight-click: §7Casts a Healing Blossom which grants §9Regeneration §b(Costs 10 Mana)"
      ]
    },
    "glowCondition": {
      "fixedValue": false
    },
    "guiBoundTo": "<NONE>",
    "inventorySize": 9,
    "inventoryStackSize": 64,
    "onRightClickedInAir": {
      "name": "BlossomFloraRightclicked"
    },
    "enableRanged": false,
    "shootConstantly": false,
    "projectile": {
      "value": "CUSTOM:FlameProjectileProjectile"
    },
    "isFood": false,
    "nutritionalValue": 4,
    "saturation": 0.3,
    "eatResultItem": {
      "value": ""
    },
    "isMeat": false,
    "isAlwaysEdible": false,
    "animation": "none"
  }
}